[
  {
    "title": "Connection Settings",
    "fields": [
      {
        "type": "textInput",
        "label": "Region",
        "value": "region",
        "regex": ".*",
        "required": true,
        "placeholder": "e.g: us-east-1"
      },
      {
        "type": "textInput",
        "label": "Stream Name",
        "value": "stream",
        "regex": ".*",
        "required": true,
        "placeholder": "e.g: test-stream"
      },
      {
        "type": "textInput",
        "label": "AWS Access Key ID",
        "value": "accessKeyID",
        "regex": ".*",
        "required": false,
        "placeholder": "e.g: access-key-id",
        "secret": true
      },
      {
        "type": "textInput",
        "label": "AWS Secret Access Key",
        "value": "accessKey",
        "regex": ".*",
        "required": false,
        "placeholder": "e.g: secret-access-key",
        "secret": true
      },
      {
        "type": "checkbox",
        "label": "Use MessageId as Partition Key",
        "value": "useMessageId",
        "default": false
      }
    ]
  }
]